{
  "status": 1,
  "msg": "成功",
  "data": {
    "result": null,
    "xmlDateMonth": "2026年03月",
    "xmlDateDay": "2026年4月21日",
    "dataMj": [
      {
        "name": "南山",
        "value": 4520.56
      },
      {
        "name": "福田",
        "value": 6178.09
      },
      {
        "name": "龙岗",
        "value": 15023.58
      },
      {
        "name": "宝安",
        "value": 4553.24
      },
      {
        "name": "罗湖",
        "value": 4875.59
      },
      {
        "name": "盐田",
        "value": 1028.41
      },
      {
        "name": "龙华",
        "value": 3701.57
      },
      {
        "name": "坪山",
        "value": 564.88
      },
      {
        "name": "光明",
        "value": 906.79
      },
      {
        "name": "大鹏",
        "value": 89.45
      },
      {
        "name": "深汕",
        "value": 0
      }
    ],
    "dataTs": [
      {
        "name": "南山",
        "value": 44
      },
      {
        "name": "福田",
        "value": 70
      },
      {
        "name": "龙岗",
        "value": 97
      },
      {
        "name": "宝安",
        "value": 43
      },
      {
        "name": "罗湖",
        "value": 48
      },
      {
        "name": "盐田",
        "value": 11
      },
      {
        "name": "龙华",
        "value": 41
      },
      {
        "name": "坪山",
        "value": 6
      },
      {
        "name": "光明",
        "value": 12
      },
      {
        "name": "大鹏",
        "value": 2
      },
      {
        "name": "深汕",
        "value": 0
      }
    ],
    "dataTotalMj": 41442.16,
    "dataTotalTs": 374
  }
}