{
  "status": 1,
  "msg": "成功",
  "data": {
    "result": null,
    "xmlDateMonth": "2025年09月",
    "xmlDateDay": "2025年10月23日",
    "dataMj": [
      {
        "name": "南山",
        "value": 279.17
      },
      {
        "name": "福田",
        "value": 358.96
      },
      {
        "name": "龙岗",
        "value": 1664.54
      },
      {
        "name": "宝安",
        "value": 1247.16
      },
      {
        "name": "罗湖",
        "value": 108.56
      },
      {
        "name": "盐田",
        "value": 0
      },
      {
        "name": "龙华",
        "value": 3438.39
      },
      {
        "name": "光明",
        "value": 3412.44
      },
      {
        "name": "大鹏",
        "value": 0
      },
      {
        "name": "坪山",
        "value": 686.8
      },
      {
        "name": "深汕",
        "value": 0
      }
    ],
    "dataTs": [
      {
        "name": "南山",
        "value": 3
      },
      {
        "name": "福田",
        "value": 2
      },
      {
        "name": "龙岗",
        "value": 19
      },
      {
        "name": "宝安",
        "value": 11
      },
      {
        "name": "罗湖",
        "value": 1
      },
      {
        "name": "盐田",
        "value": 0
      },
      {
        "name": "龙华",
        "value": 34
      },
      {
        "name": "光明",
        "value": 37
      },
      {
        "name": "大鹏",
        "value": 0
      },
      {
        "name": "坪山",
        "value": 9
      },
      {
        "name": "深汕",
        "value": 0
      }
    ],
    "dataTotalMj": 11196.02,
    "dataTotalTs": 116
  }
}