{
  "status": 1,
  "msg": "成功",
  "data": {
    "result": null,
    "xmlDateMonth": "2025年10月",
    "xmlDateDay": "2025年11月09日",
    "dataMj": [
      {
        "name": "南山",
        "value": 9608.35
      },
      {
        "name": "福田",
        "value": 6927.5
      },
      {
        "name": "龙岗",
        "value": 31123.13
      },
      {
        "name": "宝安",
        "value": 30613.33
      },
      {
        "name": "罗湖",
        "value": 3084.01
      },
      {
        "name": "盐田",
        "value": 1039.32
      },
      {
        "name": "龙华",
        "value": 34155.58
      },
      {
        "name": "光明",
        "value": 38169.11
      },
      {
        "name": "大鹏",
        "value": 0
      },
      {
        "name": "坪山",
        "value": 12423.08
      },
      {
        "name": "深汕",
        "value": 664.05
      }
    ],
    "dataTs": [
      {
        "name": "南山",
        "value": 80
      },
      {
        "name": "福田",
        "value": 44
      },
      {
        "name": "龙岗",
        "value": 339
      },
      {
        "name": "宝安",
        "value": 284
      },
      {
        "name": "罗湖",
        "value": 30
      },
      {
        "name": "盐田",
        "value": 11
      },
      {
        "name": "龙华",
        "value": 348
      },
      {
        "name": "光明",
        "value": 400
      },
      {
        "name": "大鹏",
        "value": 0
      },
      {
        "name": "坪山",
        "value": 147
      },
      {
        "name": "深汕",
        "value": 7
      }
    ],
    "dataTotalMj": 167807.46,
    "dataTotalTs": 1690
  }
}