{
  "status": 1,
  "msg": "成功",
  "data": {
    "result": null,
    "xmlDateMonth": "2025年12月",
    "xmlDateDay": "2026年1月9日",
    "dataMj": [
      {
        "name": "南山",
        "value": 2262.11
      },
      {
        "name": "福田",
        "value": 92.13
      },
      {
        "name": "龙岗",
        "value": 1224.76
      },
      {
        "name": "宝安",
        "value": 903.18
      },
      {
        "name": "罗湖",
        "value": 0
      },
      {
        "name": "盐田",
        "value": 0
      },
      {
        "name": "龙华",
        "value": 1048.2
      },
      {
        "name": "光明",
        "value": 1199.75
      },
      {
        "name": "大鹏",
        "value": 0
      },
      {
        "name": "坪山",
        "value": 1488.63
      },
      {
        "name": "深汕",
        "value": 0
      }
    ],
    "dataTs": [
      {
        "name": "南山",
        "value": 10
      },
      {
        "name": "福田",
        "value": 1
      },
      {
        "name": "龙岗",
        "value": 10
      },
      {
        "name": "宝安",
        "value": 8
      },
      {
        "name": "罗湖",
        "value": 0
      },
      {
        "name": "盐田",
        "value": 0
      },
      {
        "name": "龙华",
        "value": 10
      },
      {
        "name": "光明",
        "value": 11
      },
      {
        "name": "大鹏",
        "value": 0
      },
      {
        "name": "坪山",
        "value": 17
      },
      {
        "name": "深汕",
        "value": 0
      }
    ],
    "dataTotalMj": 8218.76,
    "dataTotalTs": 67
  }
}