{
  "status": 1,
  "msg": "成功",
  "data": {
    "result": null,
    "xmlDateMonth": "2025年12月",
    "xmlDateDay": "2026年1月14日",
    "dataMj": [
      {
        "name": "南山",
        "value": 6141.28
      },
      {
        "name": "福田",
        "value": 4998.77
      },
      {
        "name": "龙岗",
        "value": 5550.6
      },
      {
        "name": "宝安",
        "value": 4541.97
      },
      {
        "name": "罗湖",
        "value": 3126.3
      },
      {
        "name": "盐田",
        "value": 826.87
      },
      {
        "name": "龙华",
        "value": 3441.51
      },
      {
        "name": "坪山",
        "value": 1236.8
      },
      {
        "name": "光明",
        "value": 598.41
      },
      {
        "name": "大鹏",
        "value": 216.03
      },
      {
        "name": "深汕",
        "value": 0
      }
    ],
    "dataTs": [
      {
        "name": "南山",
        "value": 53
      },
      {
        "name": "福田",
        "value": 59
      },
      {
        "name": "龙岗",
        "value": 56
      },
      {
        "name": "宝安",
        "value": 47
      },
      {
        "name": "罗湖",
        "value": 45
      },
      {
        "name": "盐田",
        "value": 8
      },
      {
        "name": "龙华",
        "value": 30
      },
      {
        "name": "坪山",
        "value": 15
      },
      {
        "name": "光明",
        "value": 6
      },
      {
        "name": "大鹏",
        "value": 1
      },
      {
        "name": "深汕",
        "value": 0
      }
    ],
    "dataTotalMj": 30678.54,
    "dataTotalTs": 320
  }
}